EntroPi.py
entropi-0.2.1.dist-info/WHEEL
entropi-0.2.1.dist-info/METADATA
entropi-0.2.1.dist-info/RECORD
